Metadata-Version: 2.1
Name: fonc
Version: 0.2.0
Summary: anonymous inline functions in python
Home-page: https://github.com/j6k4m8/fonc
Author: Jordan Matelsky
Author-email: code-garbage@matelsky.com
License: MIT
Platform: UNKNOWN
Classifier: License :: OSI Approved :: MIT License
Classifier: Programming Language :: Python
Classifier: Programming Language :: Python :: 3
Classifier: Programming Language :: Python :: 3.6
Requires-Python: >=3.6.0
Provides-Extra: dev
